[{"verseId":"eob_nt_1-john_1_1","translationId":"eob_nt","testament":"NT","bookIndex":23,"bookName":"1 John","bookAbbrev":"1-john","chapter":1,"verse":1,"text":"That|strong=\"G3739\"which|strong=\"G3739\"was|strong=\"G1510\"from|strong=\"G2532\"the|strong=\"G2532\"beginning, that|strong=\"G3739\"which|strong=\"G3739\"we|strong=\"G2249\"have|strong=\"G2532\"heard, that|strong=\"G3739\"which|strong=\"G3739\"we|strong=\"G2249\"have|strong=\"G2532\"seen|strong=\"G3708\"with|strong=\"G2532\"our|strong=\"G2532\"eyes|strong=\"G3788\", that|strong=\"G3739\"which|strong=\"G3739\"we|strong=\"G2249\"saw|strong=\"G3708\", and|strong=\"G2532\"our|strong=\"G2532\"hands|strong=\"G5495\"touched|strong=\"G5584\", concerning|strong=\"G4012\"the|strong=\"G2532\"Word|strong=\"G3056\"of|strong=\"G4012\"life|strong=\"G2222\"","searchKeywords":["that","strong","g3739","which","was","g1510","from","g2532","the","beginning","g2249","have","heard","seen","g3708","with","our","eyes","g3788","saw","and","hands","g5495","touched","g5584","concerning","g4012","word","g3056","life","g2222"]},{"verseId":"eob_nt_1-john_1_2","translationId":"eob_nt","testament":"NT","bookIndex":23,"bookName":"1 John","bookAbbrev":"1-john","chapter":1,"verse":2,"text":"(and|strong=\"G2532\"the|strong=\"G2532\"life|strong=\"G2222\"was|strong=\"G1510\"revealed|strong=\"G5319\", and|strong=\"G2532\"we|strong=\"G2249\"have|strong=\"G2532\"seen|strong=\"G3708\", and|strong=\"G2532\"testify|strong=\"G3140\", and|strong=\"G2532\"declare to|strong=\"G4314\"you|strong=\"G5210\"the|strong=\"G2532\"life|strong=\"G2222\", the|strong=\"G2532\"eternal life|strong=\"G2222\", which|strong=\"G3588\"was|strong=\"G1510\"with|strong=\"G4314\"the|strong=\"G2532\"Father|strong=\"G3962\", and|strong=\"G2532\"was|strong=\"G1510\"revealed|strong=\"G5319\"to|strong=\"G4314\"us|strong=\"G2249\");","searchKeywords":["and","strong","g2532","the","life","g2222","was","g1510","revealed","g5319","g2249","have","seen","g3708","testify","g3140","declare","g4314","you","g5210","eternal","which","g3588","with","father","g3962"]},{"verseId":"eob_nt_1-john_1_3","translationId":"eob_nt","testament":"NT","bookIndex":23,"bookName":"1 John","bookAbbrev":"1-john","chapter":1,"verse":3,"text":"that|strong=\"G2443\"which|strong=\"G3739\"we|strong=\"G2249\"have|strong=\"G2192\"seen|strong=\"G3708\"and|strong=\"G2532\"heard we|strong=\"G2249\"declare to|strong=\"G2443\"you|strong=\"G5210\", that|strong=\"G2443\"you|strong=\"G5210\"also|strong=\"G2532\"may|strong=\"G2532\"have|strong=\"G2192\"fellowship|strong=\"G2842\"with|strong=\"G3326\"us|strong=\"G2249\". Yes|strong=\"G1161\", and|strong=\"G2532\"our|strong=\"G2424\"fellowship|strong=\"G2842\"is|strong=\"G3588\"with|strong=\"G3326\"the|strong=\"G2532\"Father|strong=\"G3962\"and|strong=\"G2532\"with|strong=\"G3326\"his|strong=\"G3708\"Son|strong=\"G5207\", Jesus|strong=\"G2424\"Christ|strong=\"G5547\".+ 1:3 “Christ” means “Anointed One”.","searchKeywords":["that","strong","g2443","which","g3739","g2249","have","g2192","seen","g3708","and","g2532","heard","declare","you","g5210","also","may","fellowship","g2842","with","g3326","yes","g1161","our","g2424","g3588","the","father","g3962","his","son","g5207","jesus","christ","g5547","means","anointed","one"]},{"verseId":"eob_nt_1-john_1_4","translationId":"eob_nt","testament":"NT","bookIndex":23,"bookName":"1 John","bookAbbrev":"1-john","chapter":1,"verse":4,"text":"And|strong=\"G2532\"we|strong=\"G2249\"write|strong=\"G1125\"these|strong=\"G3778\"things|strong=\"G3778\"to|strong=\"G2443\"you|strong=\"G1510\", that|strong=\"G2443\"our|strong=\"G2532\"joy|strong=\"G5479\"may|strong=\"G2532\"be|strong=\"G1510\"fulfilled|strong=\"G4137\".","searchKeywords":["and","strong","g2532","g2249","write","g1125","these","g3778","things","g2443","you","g1510","that","our","joy","g5479","may","fulfilled","g4137"]},{"verseId":"eob_nt_1-john_1_5","translationId":"eob_nt","testament":"NT","bookIndex":23,"bookName":"1 John","bookAbbrev":"1-john","chapter":1,"verse":5,"text":"This|strong=\"G3778\"is|strong=\"G1510\"the|strong=\"G1722\"message which|strong=\"G3739\"we|strong=\"G3739\"have|strong=\"G2532\"heard from|strong=\"G2532\"him|strong=\"G3588\"and|strong=\"G2532\"announce to|strong=\"G2532\"you|strong=\"G5210\", that|strong=\"G3754\"God|strong=\"G2316\"is|strong=\"G1510\"light|strong=\"G5457\", and|strong=\"G2532\"in|strong=\"G1722\"him|strong=\"G3588\"is|strong=\"G1510\"no|strong=\"G3756\"darkness|strong=\"G4653\"at|strong=\"G1722\"all|strong=\"G2532\".","searchKeywords":["this","strong","g3778","g1510","the","g1722","message","which","g3739","have","g2532","heard","from","him","g3588","and","announce","you","g5210","that","g3754","god","g2316","light","g5457","g3756","darkness","g4653","all"]},{"verseId":"eob_nt_1-john_1_6","translationId":"eob_nt","testament":"NT","bookIndex":23,"bookName":"1 John","bookAbbrev":"1-john","chapter":1,"verse":6,"text":"If|strong=\"G1437\"we|strong=\"G1437\"say|strong=\"G3004\"that|strong=\"G3754\"we|strong=\"G1437\"have|strong=\"G2192\"fellowship|strong=\"G2842\"with|strong=\"G3326\"him|strong=\"G3588\"and|strong=\"G2532\"walk|strong=\"G4043\"in|strong=\"G1722\"the|strong=\"G1722\"darkness|strong=\"G4655\", we|strong=\"G1437\"lie|strong=\"G5574\"and|strong=\"G2532\"don’t|strong=\"G3588\"tell|strong=\"G3004\"the|strong=\"G1722\"truth.","searchKeywords":["strong","g1437","say","g3004","that","g3754","have","g2192","fellowship","g2842","with","g3326","him","g3588","and","g2532","walk","g4043","g1722","the","darkness","g4655","lie","g5574","don","tell","truth"]},{"verseId":"eob_nt_1-john_1_7","translationId":"eob_nt","testament":"NT","bookIndex":23,"bookName":"1 John","bookAbbrev":"1-john","chapter":1,"verse":7,"text":"But|strong=\"G1161\"if|strong=\"G1437\"we|strong=\"G2249\"walk|strong=\"G4043\"in|strong=\"G1722\"the|strong=\"G1722\"light|strong=\"G5457\"as|strong=\"G5613\"he|strong=\"G2532\"is|strong=\"G1510\"in|strong=\"G1722\"the|strong=\"G1722\"light|strong=\"G5457\", we|strong=\"G2249\"have|strong=\"G2192\"fellowship|strong=\"G2842\"with|strong=\"G3326\"one|strong=\"G3956\"another|strong=\"G3588\", and|strong=\"G2532\"the|strong=\"G1722\"blood of|strong=\"G5207\"Jesus|strong=\"G2424\"Christ|strong=\"G5613\"his|strong=\"G3956\"Son|strong=\"G5207\"cleanses|strong=\"G2511\"us|strong=\"G2249\"from|strong=\"G2532\"all|strong=\"G3956\"sin.","searchKeywords":["but","strong","g1161","g1437","g2249","walk","g4043","g1722","the","light","g5457","g5613","g2532","g1510","have","g2192","fellowship","g2842","with","g3326","one","g3956","another","g3588","and","blood","g5207","jesus","g2424","christ","his","son","cleanses","g2511","from","all","sin"]},{"verseId":"eob_nt_1-john_1_8","translationId":"eob_nt","testament":"NT","bookIndex":23,"bookName":"1 John","bookAbbrev":"1-john","chapter":1,"verse":8,"text":"If|strong=\"G1437\"we|strong=\"G2249\"say|strong=\"G3004\"that|strong=\"G3754\"we|strong=\"G2249\"have|strong=\"G2192\"no|strong=\"G3756\"sin, we|strong=\"G2249\"deceive|strong=\"G4105\"ourselves|strong=\"G1438\", and|strong=\"G2532\"the|strong=\"G1722\"truth is|strong=\"G1510\"not|strong=\"G3756\"in|strong=\"G1722\"us|strong=\"G3004\".","searchKeywords":["strong","g1437","g2249","say","g3004","that","g3754","have","g2192","g3756","sin","deceive","g4105","ourselves","g1438","and","g2532","the","g1722","truth","g1510","not"]},{"verseId":"eob_nt_1-john_1_9","translationId":"eob_nt","testament":"NT","bookIndex":23,"bookName":"1 John","bookAbbrev":"1-john","chapter":1,"verse":9,"text":"If|strong=\"G1437\"we|strong=\"G2249\"confess|strong=\"G3670\"our|strong=\"G2532\"sins, he|strong=\"G2532\"is|strong=\"G1510\"faithful|strong=\"G4103\"and|strong=\"G2532\"righteous|strong=\"G1342\"to|strong=\"G2443\"forgive us|strong=\"G2249\"the|strong=\"G2532\"sins and|strong=\"G2532\"to|strong=\"G2443\"cleanse|strong=\"G2511\"us|strong=\"G2249\"from|strong=\"G2532\"all|strong=\"G3956\"unrighteousness.","searchKeywords":["strong","g1437","g2249","confess","g3670","our","g2532","sins","g1510","faithful","g4103","and","righteous","g1342","g2443","forgive","the","cleanse","g2511","from","all","g3956","unrighteousness"]},{"verseId":"eob_nt_1-john_1_10","translationId":"eob_nt","testament":"NT","bookIndex":23,"bookName":"1 John","bookAbbrev":"1-john","chapter":1,"verse":10,"text":"If|strong=\"G1437\"we|strong=\"G2249\"say|strong=\"G3004\"that|strong=\"G3754\"we|strong=\"G2249\"haven’t|strong=\"G3588\"sinned, we|strong=\"G2249\"make|strong=\"G4160\"him|strong=\"G3588\"a|strong=\"G2532\"liar|strong=\"G5583\", and|strong=\"G2532\"his|strong=\"G1722\"word|strong=\"G3056\"is|strong=\"G1510\"not|strong=\"G3756\"in|strong=\"G1722\"us|strong=\"G3004\".","searchKeywords":["strong","g1437","g2249","say","g3004","that","g3754","haven","g3588","sinned","make","g4160","him","g2532","liar","g5583","and","his","g1722","word","g3056","g1510","not","g3756"]}]